Metadata-Version: 2.1
Name: torch-vectorized
Version: 0.1.18
Summary: A quick closed-form solution for volumetric 3x3 matrices Eigen-Decomposition with Pytorch.
Home-page: UNKNOWN
Author: Benoit Anctil-Robitaille
Author-email: benoit.anctil-robitaille.1@ens.etsmtl.ca
License: MIT
Platform: UNKNOWN
Classifier: License :: OSI Approved :: MIT License
Classifier: Programming Language :: Python :: 3
Classifier: Programming Language :: Python :: 3.7
